voikko/__init__.py
voikko/inflect_word.py
voikko/libvoikko.py
voikko/sanat.txt
voikko/subst.aff
voikko/verb.aff
voikko/voikkoinfl.py
voikko/voikkoutils.py
voikko-0.5.dist-info/DESCRIPTION.rst
voikko-0.5.dist-info/METADATA
voikko-0.5.dist-info/RECORD
voikko-0.5.dist-info/WHEEL
voikko-0.5.dist-info/metadata.json
voikko-0.5.dist-info/top_level.txt
