Metadata-Version: 2.0
Name: voikko
Version: 0.5
Summary: Python 3 version of libvoikko and the word inflecting library
Home-page: http://github.com/fergusq/voikko
Author: Harri Pitkänen and Iikka Hauhio
Author-email: iikka.hauhio@gmail.com
License: GPL
Platform: UNKNOWN
Classifier: Programming Language :: Python :: 3
Requires-Python: >=3
